bottle_postgresql.py
tests/__init__.py
tests/bottle_postgresql_test.py
bottle_postgresql-1.0.1.dist-info/LICENSE
bottle_postgresql-1.0.1.dist-info/METADATA
bottle_postgresql-1.0.1.dist-info/WHEEL
bottle_postgresql-1.0.1.dist-info/top_level.txt
bottle_postgresql-1.0.1.dist-info/RECORD
