Metadata-Version: 2.1
Name: bottle-postgresql
Version: 1.0.1
Summary: Bottle PostgreSQL is a simple adapter for PostgreSQL with connection pooling.
Home-page: https://github.com/bernardocouto/bottle-postgresql
Author: Bernardo Couto
Author-email: bernardocouto.py@gmail.com
License: MIT
Keywords: bottle database postgresql psycopg2
Platform: any
Classifier: License :: OSI Approved :: MIT License
Classifier: Operating System :: OS Independent
Classifier: Programming Language :: Python
Classifier: Programming Language :: Python :: 3
Classifier: Topic :: Database
Requires-Dist: dbutils
Requires-Dist: psycopg2-binary
Requires-Dist: pystache
